setup.cfg
setup.py
pyd3netviz/__init__.py
pyd3netviz/_pyd3netviz.py
pyd3netviz.egg-info/PKG-INFO
pyd3netviz.egg-info/SOURCES.txt
pyd3netviz.egg-info/dependency_links.txt
pyd3netviz.egg-info/requires.txt
pyd3netviz.egg-info/top_level.txt
pyd3netviz/js/d3.min.js
pyd3netviz/js/force_layout.js