Metadata-Version: 1.0
Name: pyd3netviz
Version: 0.1.2
Summary: Simple wrapper around d3 force graph for python and Jupyter Notebooks
Home-page: https://github.com/gte620v/pyd3netviz
Author: Bob Baxley
Author-email: bob.baxley@gmail.com
License: MIT
Keywords: network graph,d3js,visualization,force layout,Jupyter Notebook
Platform: UNKNOWN
